cnba/__init__.py
cnba/__main__.py
cnba/commands/__init__.py
cnba/commands/annotate.py
cnba/commands/community.py
cnba/commands/helper.py
cnba/commands/init.py
cnba/commands/randomize.py
cnba/commands/read.py
cnba-1.0.2.dist-info/METADATA
cnba-1.0.2.dist-info/WHEEL
cnba-1.0.2.dist-info/entry_points.txt
cnba-1.0.2.dist-info/top_level.txt
cnba-1.0.2.dist-info/RECORD
